{
	"juci-diagnostics": {
		"description": "JUCI Diagnostics module",
		"read": {
			"ubus": {
				"juci.diagnostics": [
					"ping",
					"traceroute",
					"tptest_start",
					"tptest_stop",
					"tptest_packet_size",
					"tptest_running"
				]
			},
			"uci": [
				"speedtest"	
			],
			"owsd": [
				"diagnostics.speedtest",
				"diagnostics.ping",
				"diagnostics.ping6",
				"diagnostics.traceroute",
				"diagnostics.traceroute6"
			]
		},
		"write": {
			"uci": [
				"speedtest"
			]
		}
	}
}
